{"stats":{"minecraft:mined":{"minecraft:diamond_ore":17,"minecraft:cobblestone_stairs":1,"minecraft:obsidian":24,"minecraft:granite":61,"minecraft:acacia_log":65,"minecraft:grass_block":65,"minecraft:hopper":3,"minecraft:oak_wall_sign":1,"minecraft:sandstone":2,"minecraft:spawner":1,"minecraft:magma_block":10,"minecraft:redstone_ore":35,"minecraft:furnace":3,"minecraft:iron_ore":251,"minecraft:andesite":126,"minecraft:enchanting_table":1,"minecraft:bookshelf":2,"minecraft:rail":20,"minecraft:stone":2279,"minecraft:acacia_leaves":9,"minecraft:dandelion":1,"minecraft:crafting_table":4,"minecraft:torch":19,"minecraft:chest":2,"minecraft:glass":9,"minecraft:nether_quartz_ore":45,"minecraft:cobblestone":4,"minecraft:lapis_ore":13,"minecraft:oak_planks":1,"minecraft:sugar_cane":35,"minecraft:diorite":127,"minecraft:wall_torch":22,"minecraft:cobblestone_wall":6,"minecraft:grass":50,"minecraft:oak_log":35,"minecraft:coal_ore":205,"minecraft:gravel":13,"minecraft:sand":266,"minecraft:dirt":145,"minecraft:cobweb":44,"minecraft:netherrack":9,"minecraft:gold_ore":45,"minecraft:oak_leaves":13},"minecraft:picked_up":{"minecraft:crafting_table":4,"minecraft:chicken":4,"minecraft:string":51,"minecraft:pufferfish":4,"minecraft:oak_sign":1,"minecraft:beef":29,"minecraft:iron_pickaxe":1,"minecraft:light_gray_wool":1,"minecraft:chest":2,"minecraft:sugar_cane":69,"minecraft:egg":3,"minecraft:furnace":3,"minecraft:stick":5,"minecraft:torch":54,"minecraft:acacia_log":62,"minecraft:porkchop":2,"minecraft:diorite":116,"minecraft:redstone":141,"minecraft:arrow":11,"minecraft:rotten_flesh":28,"minecraft:mutton":4,"minecraft:obsidian":24,"minecraft:rail":24,"minecraft:cod":16,"minecraft:white_wool":1,"minecraft:cobblestone":1682,"minecraft:enchanting_table":1,"minecraft:magma_block":10,"minecraft:feather":6,"minecraft:cooked_beef":5,"minecraft:andesite":109,"minecraft:water_bucket":1,"minecraft:salmon":9,"minecraft:leather":15,"minecraft:potato":2,"minecraft:flint":1,"minecraft:oak_log":35,"minecraft:gunpowder":4,"minecraft:cobblestone_wall":7,"minecraft:cobblestone_stairs":57,"minecraft:dirt":187,"minecraft:lapis_lazuli":76,"minecraft:glass":64,"minecraft:bone":17,"minecraft:kelp":29,"minecraft:bow":1,"minecraft:wheat_seeds":4,"minecraft:iron_ingot":62,"minecraft:iron_ore":284,"minecraft:oak_planks":1,"minecraft:acacia_sapling":3,"minecraft:soul_sand":2,"minecraft:book":6,"minecraft:quartz":45,"minecraft:gravel":11,"minecraft:sand":628,"minecraft:gold_ore":45,"minecraft:diamond":17,"minecraft:stone_axe":1,"minecraft:granite":42,"minecraft:oak_sapling":5,"minecraft:netherrack":9,"minecraft:coal":230,"minecraft:hopper":3},"minecraft:crafted":{"minecraft:oak_planks":140,"minecraft:barrel":9,"minecraft:oak_sign":12,"minecraft:fishing_rod":4,"minecraft:furnace":3,"minecraft:acacia_fence_gate":1,"minecraft:blast_furnace":1,"minecraft:cobblestone_stairs":76,"minecraft:bookshelf":6,"minecraft:flint_and_steel":1,"minecraft:hopper":2,"minecraft:iron_boots":1,"minecraft:iron_axe":1,"minecraft:stone_pickaxe":3,"minecraft:cobblestone_wall":384,"minecraft:chest":7,"minecraft:cooked_beef":26,"minecraft:crafting_table":7,"minecraft:enchanting_table":1,"minecraft:acacia_slab":24,"minecraft:wooden_pickaxe":2,"minecraft:iron_helmet":1,"minecraft:iron_sword":2,"minecraft:bucket":4,"minecraft:stone_axe":1,"minecraft:iron_chestplate":1,"minecraft:book":13,"minecraft:paper":42,"minecraft:diamond_pickaxe":1,"minecraft:stick":124,"minecraft:iron_ingot":92,"minecraft:iron_pickaxe":14,"minecraft:stone_sword":2,"minecraft:iron_shovel":2,"minecraft:iron_leggings":1,"minecraft:acacia_planks":248,"minecraft:torch":164},"minecraft:broken":{"minecraft:iron_shovel":1,"minecraft:stone_pickaxe":3,"minecraft:iron_pickaxe":11},"minecraft:used":{"minecraft:stone_sword":107,"minecraft:enchanting_table":2,"minecraft:iron_shovel":327,"minecraft:flint_and_steel":2,"minecraft:oak_sign":5,"minecraft:chest":7,"minecraft:iron_sword":318,"minecraft:rotten_flesh":5,"minecraft:netherrack":9,"minecraft:torch":213,"minecraft:soul_sand":2,"minecraft:dirt":34,"minecraft:hopper":5,"minecraft:cobblestone_wall":359,"minecraft:acacia_sapling":3,"minecraft:granite":18,"minecraft:obsidian":10,"minecraft:glass":120,"minecraft:bookshelf":6,"minecraft:iron_axe":54,"minecraft:barrel":9,"minecraft:magma_block":6,"minecraft:furnace":5,"minecraft:cooked_cod":1,"minecraft:cooked_beef":22,"minecraft:water_bucket":136,"minecraft:diorite":6,"minecraft:cobblestone_stairs":35,"minecraft:stone_pickaxe":392,"minecraft:oak_planks":63,"minecraft:wooden_pickaxe":29,"minecraft:sugar_cane":25,"minecraft:crafting_table":11,"minecraft:blast_furnace":1,"minecraft:diamond_pickaxe":24,"minecraft:iron_pickaxe":2886,"minecraft:gravel":9,"minecraft:acacia_fence_gate":1,"minecraft:stone_axe":45,"minecraft:fishing_rod":35,"minecraft:cobblestone":93,"minecraft:bucket":140,"minecraft:andesite":34,"minecraft:smooth_stone":24},"minecraft:killed_by":{"minecraft:player":1,"minecraft:zombie":1},"minecraft:custom":{"minecraft:mob_kills":75,"minecraft:inspect_hopper":16,"minecraft:interact_with_crafting_table":56,"minecraft:open_barrel":2,"minecraft:leave_game":2,"minecraft:time_since_death":284420,"minecraft:sprint_one_cm":346448,"minecraft:walk_one_cm":618109,"minecraft:drop":18,"minecraft:deaths":2,"minecraft:sneak_time":486,"minecraft:walk_under_water_one_cm":114900,"minecraft:jump":2576,"minecraft:interact_with_blast_furnace":5,"minecraft:walk_on_water_one_cm":77437,"minecraft:enchant_item":3,"minecraft:interact_with_furnace":39,"minecraft:play_one_minute":292928,"minecraft:sleep_in_bed":1,"minecraft:time_since_rest":34500,"minecraft:damage_taken":2688,"minecraft:damage_dealt":13148,"minecraft:swim_one_cm":1868,"minecraft:fly_one_cm":308238,"minecraft:open_chest":99,"minecraft:crouch_one_cm":568,"minecraft:fish_caught":29,"minecraft:fall_one_cm":39400},"minecraft:killed":{"minecraft:spider":2,"minecraft:phantom":4,"minecraft:skeleton":12,"minecraft:chicken":4,"minecraft:pig":1,"minecraft:creeper":1,"minecraft:sheep":4,"minecraft:zombie":28,"minecraft:enderman":2,"minecraft:cow":16},"minecraft:dropped":{"minecraft:water_bucket":1,"minecraft:wheat_seeds":1,"minecraft:lapis_lazuli":1,"minecraft:cooked_beef":5,"minecraft:cobblestone":128,"minecraft:granite":8,"minecraft:cobblestone_stairs":56,"minecraft:dirt":50,"minecraft:iron_pickaxe":1,"minecraft:redstone":9,"minecraft:cobblestone_wall":1,"minecraft:gunpowder":2}},"DataVersion":2230}